usrse/__init__.py
usrse/defaults.py
usrse/logger.py
usrse/version.py
usrse/client/__init__.py
usrse/client/get.py
usrse/client/listing.py
usrse/client/shell.py
usrse/main/__init__.py
usrse/main/client.py
usrse/main/endpoints.py
usrse/tests/__init__.py
usrse/tests/helpers.sh
usrse/tests/test_client.py
usrse/tests/test_client.sh
usrse/tests/test_utils.py
usrse/utils/__init__.py
usrse/utils/fileio.py
usrse/utils/terminal.py
usrse-0.0.11.dist-info/LICENSE
usrse-0.0.11.dist-info/METADATA
usrse-0.0.11.dist-info/WHEEL
usrse-0.0.11.dist-info/entry_points.txt
usrse-0.0.11.dist-info/top_level.txt
usrse-0.0.11.dist-info/RECORD
