Metadata-Version: 2.1
Name: usrse
Version: 0.0.11
Summary: Python client for programmatic access to usrse events
Home-page: https://github.com/usrse/usrse-python
Author: Vanessa Sochat
Author-email: vsoch@users.noreply.github.com
Maintainer: Vanessa Sochat
License: LICENSE
Keywords: usrse,rseng,events
Platform: UNKNOWN
Classifier: Intended Audience :: Science/Research
Classifier: Intended Audience :: Developers
Classifier: License :: OSI Approved :: Mozilla Public License 2.0 (MPL 2.0)
Classifier: Programming Language :: C
Classifier: Programming Language :: Python
Classifier: Topic :: Software Development
Classifier: Topic :: Scientific/Engineering
Classifier: Operating System :: Unix
Classifier: Programming Language :: Python :: 3.3
License-File: LICENSE
Requires-Dist: requests
Requires-Dist: rich
Provides-Extra: all
Requires-Dist: requests ; extra == 'all'
Requires-Dist: rich ; extra == 'all'
Requires-Dist: pytest (>=4.6.2) ; extra == 'all'
